py_resilio_connect/__init__.py
py_resilio_connect/agents.py
py_resilio_connect/app.py
py_resilio_connect/communication.py
py_resilio_connect/jobs.py
py_resilio_connect/jobs_from_csv.py
py_resilio_connect/agents/__init__.py
py_resilio_connect/agents/agents.py
py_resilio_connect/communication/__init__.py
py_resilio_connect/communication/communication.py
py_resilio_connect/jobs/__init__.py
py_resilio_connect/jobs/jobs.py
py_resilio_connect/jobs_from_csv/__init__.py
py_resilio_connect/jobs_from_csv/jobs_from_csv.py
py_resilio_connect-2.1.dist-info/METADATA
py_resilio_connect-2.1.dist-info/WHEEL
py_resilio_connect-2.1.dist-info/top_level.txt
py_resilio_connect-2.1.dist-info/RECORD
