Metadata-Version: 2.1
Name: py-resilio-connect
Version: 2.1
Summary: Generate simple Resilio Connect Sync Jobs based on a csv file
Home-page: https://github.com/ilanshamir/connect-scripts.git
Author: Ilan Shamir
Author-email: team@resilio.com
License: MIT
Platform: UNKNOWN
Requires-Dist: requests
